nampa/__init__.py
nampa/binrw.py
nampa/crc.py
nampa/flirt.py
nampa-0.1.1.data/scripts/dumpsig.py
nampa-0.1.1.dist-info/DESCRIPTION.rst
nampa-0.1.1.dist-info/METADATA
nampa-0.1.1.dist-info/RECORD
nampa-0.1.1.dist-info/WHEEL
nampa-0.1.1.dist-info/metadata.json
nampa-0.1.1.dist-info/top_level.txt
